multi_vector_simulator/A0_initialization.py
multi_vector_simulator/A1_csv_to_json.py
multi_vector_simulator/B0_data_input_json.py
multi_vector_simulator/C0_data_processing.py
multi_vector_simulator/C1_verification.py
multi_vector_simulator/C2_economic_functions.py
multi_vector_simulator/D0_modelling_and_optimization.py
multi_vector_simulator/D1_model_components.py
multi_vector_simulator/D2_model_constraints.py
multi_vector_simulator/E0_evaluation.py
multi_vector_simulator/E1_process_results.py
multi_vector_simulator/E2_economics.py
multi_vector_simulator/E3_indicator_calculation.py
multi_vector_simulator/E4_verification.py
multi_vector_simulator/F0_output.py
multi_vector_simulator/F1_plotting.py
multi_vector_simulator/F2_autoreport.py
multi_vector_simulator/F3_debug.py
multi_vector_simulator/__init__.py
multi_vector_simulator/cli.py
multi_vector_simulator/server.py
multi_vector_simulator/version.py
multi_vector_simulator/package_data/MVS_parameters_list.csv
multi_vector_simulator/package_data/assets/logo-eland-original.jpg
multi_vector_simulator/package_data/assets/styles.css
multi_vector_simulator/package_data/input_template/csv_elements/constraints.csv
multi_vector_simulator/package_data/input_template/csv_elements/economic_data.csv
multi_vector_simulator/package_data/input_template/csv_elements/energyBusses.csv
multi_vector_simulator/package_data/input_template/csv_elements/energyConsumption.csv
multi_vector_simulator/package_data/input_template/csv_elements/energyConversion.csv
multi_vector_simulator/package_data/input_template/csv_elements/energyProduction.csv
multi_vector_simulator/package_data/input_template/csv_elements/energyProviders.csv
multi_vector_simulator/package_data/input_template/csv_elements/energyStorage.csv
multi_vector_simulator/package_data/input_template/csv_elements/fixcost.csv
multi_vector_simulator/package_data/input_template/csv_elements/project_data.csv
multi_vector_simulator-1.1.1.dist-info/LICENSE.md
multi_vector_simulator-1.1.1.dist-info/METADATA
multi_vector_simulator-1.1.1.dist-info/WHEEL
multi_vector_simulator-1.1.1.dist-info/entry_points.txt
multi_vector_simulator-1.1.1.dist-info/top_level.txt
multi_vector_simulator-1.1.1.dist-info/RECORD
