Metadata-Version: 2.1
Name: multi-vector-simulator
Version: 1.1.1
Summary: Multi-vector Simulation Tool assessing and optimizing Local Energy Systems (LES) for the E-LAND project
Home-page: https://github.com/rl-institut/multi-vector-simulator
Author: Reiner Lemoine Institut
Author-email: pypi@rl-institut.de
Project-URL: Bug Reports, https://github.com/rl-institut/multi-vector-simulator/issues
Project-URL: Source, https://github.com/rl-institut/multi-vector-simulator
Keywords: multi-vector local-energy-systems
Classifier: Development Status :: 3 - Alpha
Classifier: Intended Audience :: Developers
Classifier: Topic :: Software Development :: Build Tools
Classifier: License :: OSI Approved :: GNU General Public License v2 (GPLv2)
Classifier: Programming Language :: Python :: 3
Classifier: Programming Language :: Python :: 3.5
Classifier: Programming Language :: Python :: 3.6
Classifier: Programming Language :: Python :: 3.7
Classifier: Programming Language :: Python :: 3.8
Requires-Python: >=3.6, <4
License-File: LICENSE.md
Requires-Dist: graphviz >=0.14.1
Requires-Dist: plotly
Requires-Dist: psutil
Requires-Dist: kaleido >=0.0.2
Requires-Dist: openpyxl >=3.0.5
Requires-Dist: xlrd ==1.2.0
Requires-Dist: oemof.solph ==0.5.1
Requires-Dist: oemof.network ==0.5.0a5
Provides-Extra: docs
Requires-Dist: sphinx >=2.3.1 ; extra == 'docs'
Requires-Dist: sphinx-rtd-theme >=0.4.3 ; extra == 'docs'
Requires-Dist: numpydoc >=1.1.0 ; extra == 'docs'
Requires-Dist: sphinxcontrib-svg2pdfconverter ; extra == 'docs'
Provides-Extra: report
Requires-Dist: dash >=2.3.1 ; extra == 'report'
Requires-Dist: kaleido >=0.0.2 ; extra == 'report'
Requires-Dist: folium >=0.10.1 ; extra == 'report'
Requires-Dist: reverse-geocoder >=1.5.1 ; extra == 'report'
Requires-Dist: staticmap >=0.5.4 ; extra == 'report'
Requires-Dist: pyppeteer >=0.2.2 ; extra == 'report'
Requires-Dist: psutil >=5.7.0 ; extra == 'report'
Provides-Extra: test
Requires-Dist: pytest >=5.3.1 ; extra == 'test'
Requires-Dist: black ==24.3.0 ; extra == 'test'
Requires-Dist: coverage >=4.5 ; extra == 'test'
Requires-Dist: coveralls >=3.0.1 ; extra == 'test'
Requires-Dist: mock >=3.0.5 ; extra == 'test'
Requires-Dist: click ==8.0.2 ; extra == 'test'
